odoo10_addon_sale_packaging-10.0.1.0.2-py3.8-nspkg.pth
odoo/addons/sale_packaging/README.rst
odoo/addons/sale_packaging/__init__.py
odoo/addons/sale_packaging/__manifest__.py
odoo/addons/sale_packaging/i18n/ca.po
odoo/addons/sale_packaging/i18n/cs_CZ.po
odoo/addons/sale_packaging/i18n/de.po
odoo/addons/sale_packaging/i18n/es.po
odoo/addons/sale_packaging/i18n/es_MX.po
odoo/addons/sale_packaging/i18n/fi.po
odoo/addons/sale_packaging/i18n/fr.po
odoo/addons/sale_packaging/i18n/gl.po
odoo/addons/sale_packaging/i18n/hr.po
odoo/addons/sale_packaging/i18n/it.po
odoo/addons/sale_packaging/i18n/nl_NL.po
odoo/addons/sale_packaging/i18n/pt.po
odoo/addons/sale_packaging/i18n/pt_BR.po
odoo/addons/sale_packaging/i18n/pt_PT.po
odoo/addons/sale_packaging/i18n/ro.po
odoo/addons/sale_packaging/i18n/sale_packaging.pot
odoo/addons/sale_packaging/i18n/sk.po
odoo/addons/sale_packaging/i18n/sl.po
odoo/addons/sale_packaging/i18n/tr.po
odoo/addons/sale_packaging/i18n/tr_TR.po
odoo/addons/sale_packaging/i18n/vi_VN.po
odoo/addons/sale_packaging/i18n/zh_CN.po
odoo/addons/sale_packaging/models/__init__.py
odoo/addons/sale_packaging/models/procurement_order.py
odoo/addons/sale_packaging/models/procurement_rule.py
odoo/addons/sale_packaging/models/sale_order_line.py
odoo/addons/sale_packaging/models/stock_move.py
odoo/addons/sale_packaging/static/description/icon.png
odoo/addons/sale_packaging/tests/__init__.py
odoo/addons/sale_packaging/tests/test_sale_order_line.py
odoo/addons/sale_packaging/tests/test_stock_move.py
odoo/addons/sale_packaging/views/procurement_rule.xml
odoo/addons/sale_packaging/views/sale_order_line_views.xml
odoo10_addon_sale_packaging-10.0.1.0.2.dist-info/METADATA
odoo10_addon_sale_packaging-10.0.1.0.2.dist-info/WHEEL
odoo10_addon_sale_packaging-10.0.1.0.2.dist-info/namespace_packages.txt
odoo10_addon_sale_packaging-10.0.1.0.2.dist-info/top_level.txt
odoo10_addon_sale_packaging-10.0.1.0.2.dist-info/RECORD
